screenshield/__init__.py
screenshield/main.py
screenshield-0.3.dist-info/METADATA
screenshield-0.3.dist-info/WHEEL
screenshield-0.3.dist-info/top_level.txt
screenshield-0.3.dist-info/RECORD
