Metadata-Version: 2.1
Name: screenshield
Version: 0.3
Home-page: https://github.com/kevin-xie-mit/prompt-guard
Author: Kevin Xie
Author-email: kevinxie@mit.edu
License: MIT
Classifier: Programming Language :: Python :: 3
Requires-Dist: openai
Requires-Dist: tiktoken
Requires-Dist: requests
Requires-Dist: pydantic
Requires-Dist: pyyaml
Requires-Dist: pydantic-settings
